{
    "id": 128940955,
    "name": "Zonk Always Clears",
    "author": "HypeYTW",
    "creators": [],
    "verifier": "Maxr",
    "verification": "https://youtu.be/1A_SXEmj_QI",
    "percentToQualify": "100",
    "fps": "60",
    "records": [
        {
            "user": "finni1505",
            "link": "https://medal.tv/de/games/geometry-dash/clips/lGfrRN9iKIFP-L8xv?invite=cr-MSxtbngsMzY5MjUzOTQw&v=30",
            "hz": "60",
            "percent": 100
        },
        {
            "user": "FoldedZero",
            "link": "https://youtu.be/m_gtIH-aDZo",
            "hz": "60",
            "percent": 100
        }
    ]
}
